README.md
setup.py
fbp_calculator/__init__.py
fbp_calculator/__main__.py
fbp_calculator/calculatorfbp.py
fbp_calculator/dialogfbp.py
fbp_calculator/main.py
fbp_calculator/mainwindowfbp.py
fbp_calculator/reaction_adapter.py
fbp_calculator/release.py
fbp_calculator/resources_rc.py
fbp_calculator/ui_dialogfbp.py
fbp_calculator/ui_mainwindowfbp.py
fbp_calculator.egg-info/PKG-INFO
fbp_calculator.egg-info/SOURCES.txt
fbp_calculator.egg-info/dependency_links.txt
fbp_calculator.egg-info/entry_points.txt
fbp_calculator.egg-info/requires.txt
fbp_calculator.egg-info/top_level.txt
fbp_calculator/reactionsystem/__init__.py
fbp_calculator/reactionsystem/_fbs_calculated_item.py
fbp_calculator/reactionsystem/_fbs_iterate_item.py
fbp_calculator/reactionsystem/boolean_wrap.py
fbp_calculator/reactionsystem/exceptions.py
fbp_calculator/reactionsystem/reaction.py
fbp_calculator/reactionsystem/reaction_set.py
fbp_calculator/reactionsystem/reaction_system.py