Metadata-Version: 1.0
Name: fbp-calculator
Version: 1.0.18
Summary: FBP Calculator is a Python tool to calculate predicor for Reaction System.
Home-page: https://github.com/deselmo/FBP_Calculator
Author: William Guglielmo
Author-email: william@deselmo.com
License: MIT
Project-URL: Bug Reports, https://github.com/deselmo/FBP_Calculator/issues
Project-URL: Source, https://github.com/deselmo/FBP_Calculator/
Platform: UNKNOWN
